{
  "metadata": {},
  "type": "species",
  "vernacular": "Héron cendré",
  "name": "Ardea cinerea",
  "image": {
    "src": "media/Photos site/Oiseaux/Héroncendré.JPG",
    "alt": "Un héron cendré",
    "title": "Un héron cendré"
  },
  "iucn": "lc",
  "taxonomy": {
    "Règne": "Animalia",
    "Embranchement": "Chordata",
    "Sous-embranchement": "Vertebrata",
    "Classe": "Aves",
    "Ordre": "Pelecaniformes",
    "Famille": "Ardeidae",
    "Genre": "Ardea",
    "Espèce": "Ardea cinerea"
  },
  "page_content": {
    "Ponte": "Février-Juillet",
    "Répartition": "Eurasie/Afrique",
    "Habitat": "Varié mais humide",
    "Chant": "Fraaank"
  },
  "description": "Il s'agit du plus grand des Ardéidés d'Europe.<br/> On le reconnait assez facilement grâce à sa silhouette caractéristique.<br/> Le juvénile est plus terne et ne possède pas encore de huppe.",
  "sound": {
    "src": "media/Chants oiseaux/Héroncendré.ogg"
  },
  "map": {
    "src": "media/Aires/Aire_oiseaux/Aire_Héron.jpg",
    "alt": "Aire de répartition du héron cendré",
    "title": "Aire de répartition du héron cendré"
  },
  "sources": [
    "https://auvergne-rhone-alpes.lpo.fr/Heron-cendre",
    "https://www.iucnredlist.org/species/22696993/154525233",
    "https://www.oiseaux.net/oiseaux/heron.cendre.html",
    "https://fr.wikipedia.org/wiki/H%C3%A9ron_cendr%C3%A9"
  ]
}